formiq/__init__.py
formiq/__main__.py
formiq/cli.py
formiq/core.py
formiq/reporting/__init__.py
formiq/reporting/json_to_junit.py
formiq/reporting/markdown_reporter.py
formiq-0.1.7.dist-info/METADATA
formiq-0.1.7.dist-info/WHEEL
formiq-0.1.7.dist-info/entry_points.txt
formiq-0.1.7.dist-info/top_level.txt
formiq-0.1.7.dist-info/RECORD
