Metadata-Version: 2.4
Name: formiq
Version: 0.1.7
Summary: Formiq: a minimal, configurable workflow & data-quality framework
Requires-Python: >=3.10
Requires-Dist: PyYAML>=6.0
Provides-Extra: pandas
Requires-Dist: pandas>=2.0; extra == "pandas"
Provides-Extra: db
Requires-Dist: SQLAlchemy>=2.0; extra == "db"
